recovar/EM_iteration.py
recovar/__init__.py
recovar/_version.py
recovar/adaptive_homogeneous.py
recovar/adaptive_kernel_discretization.py
recovar/adaptive_kernel_two.py
recovar/command_line.py
recovar/config.py
recovar/constants.py
recovar/core.py
recovar/covariance_core.py
recovar/covariance_estimation.py
recovar/cryodrgn_load.py
recovar/cryodrgn_mrcfile.py
recovar/cryodrgn_source.py
recovar/cryodrgn_starfile.py
recovar/cryojax_map_coordinates.py
recovar/csparc_bind.py
recovar/dataset.py
recovar/deconvolve_density.py
recovar/downsample.py
recovar/embedding.py
recovar/ewald.py
recovar/fourier_transform_utils.py
recovar/heterogeneity_volume.py
recovar/homogeneous.py
recovar/image_assignment.py
recovar/jax_map_squared.py
recovar/latent_density.py
recovar/linalg.py
recovar/locres.py
recovar/mask.py
recovar/metrics.py
recovar/noise.py
recovar/nystrom_test.py
recovar/output.py
recovar/padding.py
recovar/parser_args.py
recovar/plot_utils.py
recovar/pose_refinement.py
recovar/ppca.py
recovar/principal_components.py
recovar/regularization.py
recovar/relion_functions.py
recovar/simulate_scattering_potential.py
recovar/simulator.py
recovar/small_experiment.py
recovar/synthetic_dataset.py
recovar/tilt_dataset.py
recovar/trajectory.py
recovar/utils.py
recovar/commands/analyze.py
recovar/commands/compute_embedding.py
recovar/commands/compute_state.py
recovar/commands/compute_trajectory.py
recovar/commands/estimate_conformational_density.py
recovar/commands/estimate_stable_states.py
recovar/commands/extract_image_subset.py
recovar/commands/extract_image_subset_from_kmeans.py
recovar/commands/make_spike_datasets.py
recovar/commands/make_test_dataset.py
recovar/commands/outlier_detection.py
recovar/commands/pipeline.py
recovar/commands/pipeline_with_outliers.py
recovar/commands/reconstruct_from_external_embedding.py
recovar/commands/run_test_dataset.py
recovar/data/atom_coeffs_extended.json
recovar/data/ctf_10076.pkl
recovar/data/ctf_10180.pkl
recovar/data/noise_10076.pkl
recovar-0.4.5.dist-info/LICENSE
recovar-0.4.5.dist-info/METADATA
recovar-0.4.5.dist-info/WHEEL
recovar-0.4.5.dist-info/entry_points.txt
recovar-0.4.5.dist-info/top_level.txt
recovar-0.4.5.dist-info/RECORD
