Metadata-Version: 2.2
Name: recovar
Version: 0.4.5
Summary: RECOVAR cryo-EM heterogeneity analysis
Author-email: Marc Aurele Gilles <gilles@princeton.edu>
Project-URL: Homepage, https://github.com/ma-gilles/recovar
Classifier: Programming Language :: Python :: 3
Classifier: License :: OSI Approved :: GNU General Public License v3 (GPLv3)
Classifier: Operating System :: POSIX :: Linux
Requires-Python: >=3.11
License-File: LICENSE
Requires-Dist: dataframe_image==0.2.7
Requires-Dist: finufft==2.3.1
Requires-Dist: healpy==1.18.0
Requires-Dist: ipython==8.12.3
Requires-Dist: ipywidgets==8.1.5
Requires-Dist: jax_finufft==0.1.0
Requires-Dist: jaxopt==0.8.3
Requires-Dist: jaxtyping==0.2.38
Requires-Dist: kneed==0.8.5
Requires-Dist: lineax==0.0.7
Requires-Dist: matplotlib==3.10.0
Requires-Dist: matplotlib_scalebar==0.9.0
Requires-Dist: more_itertools==10.6.0
Requires-Dist: mrcfile==1.5.4
Requires-Dist: numpy
Requires-Dist: pandas==2.2.3
Requires-Dist: plotly==6.0.0
Requires-Dist: scikit-learn==1.6.1
Requires-Dist: cufflinks
Requires-Dist: jupyterlab
Requires-Dist: notebook<7
Requires-Dist: scipy==1.15.2
Requires-Dist: seaborn==0.13.2
Requires-Dist: scikit-image
Requires-Dist: starfile==0.5.11
Requires-Dist: tensorflow_cpu==2.18.0
Requires-Dist: typing_extensions==4.12.2
Requires-Dist: twine
Requires-Dist: ipykernel
Requires-Dist: scikit-fmm
Requires-Dist: umap-learn
Provides-Extra: dev
